Metadata-Version: 2.1
Name: almighty-image-processing
Version: 0.0.1
Summary: image Processing Package using Skimage
Home-page: https://github.com/tiemi/image-processing-package
Author: AlmigthyMatheus
Requires-Python: >=3.5
Requires-Dist: scikit-image ~=0.24.0
Requires-Dist: matplotlib ~=3.9.2
Requires-Dist: numpy ~=2.1.1
